[
    {
        "name": "CortesID",
        "dbType": "bigInteger,true,true",
        "htmlType": null,
        "validations": null,
        "searchable": false,
        "fillable": false,
        "primary": true,
        "inForm": false,
        "inIndex": false,
        "inView": false
    },
    {
        "name": "NombreInsumo",
        "dbType": "string,100:nullable",
        "htmlType": "text",
        "validations": "nullable|string|max:100",
        "searchable": true,
        "fillable": true,
        "primary": false,
        "inForm": true,
        "inIndex": true,
        "inView": true
    },
    {
        "name": "Mes",
        "dbType": "string,100:nullable",
        "htmlType": "text",
        "validations": "nullable|string|max:100",
        "searchable": true,
        "fillable": true,
        "primary": false,
        "inForm": true,
        "inIndex": true,
        "inView": true
    },
    {
        "name": "A\u00f1o",
        "dbType": "date:nullable",
        "htmlType": "date",
        "validations": "nullable",
        "searchable": true,
        "fillable": true,
        "primary": false,
        "inForm": true,
        "inIndex": true,
        "inView": true
    },
    {
        "name": "Costo",
        "dbType": "decimal,10,2",
        "htmlType": null,
        "validations": "nullable|numeric",
        "searchable": true,
        "fillable": true,
        "primary": false,
        "inForm": true,
        "inIndex": true,
        "inView": true
    },
    {
        "name": "CostoTotal",
        "dbType": "decimal,10,2",
        "htmlType": null,
        "validations": "nullable|numeric",
        "searchable": true,
        "fillable": true,
        "primary": false,
        "inForm": true,
        "inIndex": true,
        "inView": true
    },
    {
        "name": "Margen",
        "dbType": "decimal,10,2",
        "htmlType": null,
        "validations": "nullable|numeric",
        "searchable": true,
        "fillable": true,
        "primary": false,
        "inForm": true,
        "inIndex": true,
        "inView": true
    },
    {
        "name": "GerenciaID",
        "dbType": "integer,false",
        "htmlType": null,
        "validations": "nullable|integer",
        "searchable": true,
        "fillable": true,
        "primary": false,
        "inForm": true,
        "inIndex": true,
        "inView": true
    },
    {
        "name": "created_at",
        "dbType": "datetime",
        "htmlType": "date",
        "validations": "required",
        "searchable": false,
        "fillable": false,
        "primary": false,
        "inForm": false,
        "inIndex": false,
        "inView": false
    },
    {
        "name": "updated_at",
        "dbType": "datetime",
        "htmlType": "date",
        "validations": "required",
        "searchable": false,
        "fillable": false,
        "primary": false,
        "inForm": false,
        "inIndex": false,
        "inView": false
    },
    {
        "name": "deleted_at",
        "dbType": "datetime:nullable",
        "htmlType": "date",
        "validations": "nullable",
        "searchable": false,
        "fillable": false,
        "primary": false,
        "inForm": false,
        "inIndex": false,
        "inView": false
    }
]